{"int":{"st":"ESERCIZIO","c_ele":1,"t_ele":"Europee","f_elet":"VOTANTI","dt_ele":20240609000000,"l_terr":"PROVINCIA","area":"I","dt_agg":20240610045333},"note":["La percentuale riportata nella colonna della precedente elezione è sempre riferita a tutte le sezioni del comune."],"note_din":null,"enti":{"ente_p":{"desc":"TARANTO","cod":78,"ele_m":224030,"ele_f":243390,"ele_t":467420,"com":[{"cod_reg":16,"com_att":4,"num_com":4}],"com_vot":[{"com":1,"dt_com":20240608230000,"enti_p":543,"enti_t":543,"perc":"11,00","vot_m":0,"vot_f":0,"vot_t":51430,"perc_r":"11,44"},{"com":2,"dt_com":20240609120000,"enti_p":543,"enti_t":543,"perc":"18,69","vot_m":0,"vot_f":0,"vot_t":87356,"perc_r":"31,39"},{"com":3,"dt_com":20240609190000,"enti_p":543,"enti_t":543,"perc":"27,56","vot_m":0,"vot_f":0,"vot_t":128842,"perc_r":"44,33"},{"com":4,"dt_com":20240609230000,"enti_p":543,"enti_t":543,"perc":"38,29","vot_m":91606,"vot_f":87384,"vot_t":178990,"perc_r":"44,33"}]},"enti_f":[{"tipo":"COMUNE","desc":"AVETRANA","cod":10,"ele_m":2581,"ele_f":2814,"ele_t":5395,"una_lis":null,"tipo_tras":"SZ","com_vot":[{"com":1,"dt_com":20240608230000,"enti_p":8,"enti_t":8,"perc":"7,25","vot_m":0,"vot_f":0,"vot_t":391,"perc_r":"9,09"},{"com":2,"dt_com":20240609120000,"enti_p":8,"enti_t":8,"perc":"13,40","vot_m":0,"vot_f":0,"vot_t":723,"perc_r":"25,27"},{"com":3,"dt_com":20240609190000,"enti_p":8,"enti_t":8,"perc":"20,04","vot_m":0,"vot_f":0,"vot_t":1081,"perc_r":"36,16"},{"com":4,"dt_com":20240609230000,"enti_p":8,"enti_t":8,"perc":"30,29","vot_m":849,"vot_f":785,"vot_t":1634,"perc_r":"36,16"}]},{"tipo":"COMUNE","desc":"CAROSINO","cod":20,"ele_m":2649,"ele_f":2819,"ele_t":5468,"una_lis":null,"tipo_tras":"SZ","com_vot":[{"com":1,"dt_com":20240608230000,"enti_p":6,"enti_t":6,"perc":"28,84","vot_m":0,"vot_f":0,"vot_t":1577,"perc_r":"20,01"},{"com":2,"dt_com":20240609120000,"enti_p":6,"enti_t":6,"perc":"42,17","vot_m":0,"vot_f":0,"vot_t":2306,"perc_r":"57,95"},{"com":3,"dt_com":20240609190000,"enti_p":6,"enti_t":6,"perc":"59,27","vot_m":0,"vot_f":0,"vot_t":3241,"perc_r":"75,72"},{"com":4,"dt_com":20240609230000,"enti_p":6,"enti_t":6,"perc":"74,41","vot_m":1997,"vot_f":2072,"vot_t":4069,"perc_r":"75,72"}]},{"tipo":"COMUNE","desc":"CASTELLANETA","cod":30,"ele_m":6691,"ele_f":7172,"ele_t":13863,"una_lis":null,"tipo_tras":"SZ","com_vot":[{"com":1,"dt_com":20240608230000,"enti_p":19,"enti_t":19,"perc":"12,31","vot_m":0,"vot_f":0,"vot_t":1706,"perc_r":"11,94"},{"com":2,"dt_com":20240609120000,"enti_p":19,"enti_t":19,"perc":"19,76","vot_m":0,"vot_f":0,"vot_t":2739,"perc_r":"32,09"},{"com":3,"dt_com":20240609190000,"enti_p":19,"enti_t":19,"perc":"27,96","vot_m":0,"vot_f":0,"vot_t":3876,"perc_r":"45,50"},{"com":4,"dt_com":20240609230000,"enti_p":19,"enti_t":19,"perc":"40,60","vot_m":2839,"vot_f":2789,"vot_t":5628,"perc_r":"45,50"}]},{"tipo":"COMUNE","desc":"CRISPIANO","cod":40,"ele_m":5493,"ele_f":5742,"ele_t":11235,"una_lis":null,"tipo_tras":"SZ","com_vot":[{"com":1,"dt_com":20240608230000,"enti_p":13,"enti_t":13,"perc":"10,04","vot_m":0,"vot_f":0,"vot_t":1128,"perc_r":"9,99"},{"com":2,"dt_com":20240609120000,"enti_p":13,"enti_t":13,"perc":"17,00","vot_m":0,"vot_f":0,"vot_t":1910,"perc_r":"29,96"},{"com":3,"dt_com":20240609190000,"enti_p":13,"enti_t":13,"perc":"24,60","vot_m":0,"vot_f":0,"vot_t":2764,"perc_r":"42,56"},{"com":4,"dt_com":20240609230000,"enti_p":13,"enti_t":13,"perc":"35,73","vot_m":2054,"vot_f":1960,"vot_t":4014,"perc_r":"42,56"}]},{"tipo":"COMUNE","desc":"FAGGIANO","cod":50,"ele_m":1369,"ele_f":1464,"ele_t":2833,"una_lis":null,"tipo_tras":"SZ","com_vot":[{"com":1,"dt_com":20240608230000,"enti_p":4,"enti_t":4,"perc":"31,94","vot_m":0,"vot_f":0,"vot_t":905,"perc_r":"26,76"},{"com":2,"dt_com":20240609120000,"enti_p":4,"enti_t":4,"perc":"49,31","vot_m":0,"vot_f":0,"vot_t":1397,"perc_r":"69,38"},{"com":3,"dt_com":20240609190000,"enti_p":4,"enti_t":4,"perc":"67,07","vot_m":0,"vot_f":0,"vot_t":1900,"perc_r":"84,55"},{"com":4,"dt_com":20240609230000,"enti_p":4,"enti_t":4,"perc":"81,22","vot_m":1147,"vot_f":1154,"vot_t":2301,"perc_r":"84,55"}]},{"tipo":"COMUNE","desc":"FRAGAGNANO","cod":60,"ele_m":2087,"ele_f":2282,"ele_t":4369,"una_lis":null,"tipo_tras":"SZ","com_vot":[{"com":1,"dt_com":20240608230000,"enti_p":5,"enti_t":5,"perc":"11,03","vot_m":0,"vot_f":0,"vot_t":482,"perc_r":"11,02"},{"com":2,"dt_com":20240609120000,"enti_p":5,"enti_t":5,"perc":"19,36","vot_m":0,"vot_f":0,"vot_t":846,"perc_r":"32,76"},{"com":3,"dt_com":20240609190000,"enti_p":5,"enti_t":5,"perc":"30,44","vot_m":0,"vot_f":0,"vot_t":1330,"perc_r":"45,43"},{"com":4,"dt_com":20240609230000,"enti_p":5,"enti_t":5,"perc":"41,75","vot_m":918,"vot_f":906,"vot_t":1824,"perc_r":"45,43"}]},{"tipo":"COMUNE","desc":"GINOSA","cod":70,"ele_m":8939,"ele_f":9121,"ele_t":18060,"una_lis":null,"tipo_tras":"SZ","com_vot":[{"com":1,"dt_com":20240608230000,"enti_p":22,"enti_t":22,"perc":"9,05","vot_m":0,"vot_f":0,"vot_t":1634,"perc_r":"9,46"},{"com":2,"dt_com":20240609120000,"enti_p":22,"enti_t":22,"perc":"14,90","vot_m":0,"vot_f":0,"vot_t":2691,"perc_r":"28,84"},{"com":3,"dt_com":20240609190000,"enti_p":22,"enti_t":22,"perc":"21,48","vot_m":0,"vot_f":0,"vot_t":3879,"perc_r":"44,47"},{"com":4,"dt_com":20240609230000,"enti_p":22,"enti_t":22,"perc":"34,47","vot_m":3312,"vot_f":2913,"vot_t":6225,"perc_r":"44,47"}]},{"tipo":"COMUNE","desc":"GROTTAGLIE","cod":80,"ele_m":12381,"ele_f":13480,"ele_t":25861,"una_lis":null,"tipo_tras":"SZ","com_vot":[{"com":1,"dt_com":20240608230000,"enti_p":27,"enti_t":27,"perc":"9,67","vot_m":0,"vot_f":0,"vot_t":2501,"perc_r":"9,59"},{"com":2,"dt_com":20240609120000,"enti_p":27,"enti_t":27,"perc":"15,97","vot_m":0,"vot_f":0,"vot_t":4130,"perc_r":"28,28"},{"com":3,"dt_com":20240609190000,"enti_p":27,"enti_t":27,"perc":"22,96","vot_m":0,"vot_f":0,"vot_t":5938,"perc_r":"42,42"},{"com":4,"dt_com":20240609230000,"enti_p":27,"enti_t":27,"perc":"33,56","vot_m":4514,"vot_f":4166,"vot_t":8680,"perc_r":"42,42"}]},{"tipo":"COMUNE","desc":"LATERZA","cod":90,"ele_m":5963,"ele_f":6255,"ele_t":12218,"una_lis":null,"tipo_tras":"SZ","com_vot":[{"com":1,"dt_com":20240608230000,"enti_p":14,"enti_t":14,"perc":"11,22","vot_m":0,"vot_f":0,"vot_t":1371,"perc_r":"8,75"},{"com":2,"dt_com":20240609120000,"enti_p":14,"enti_t":14,"perc":"17,24","vot_m":0,"vot_f":0,"vot_t":2106,"perc_r":"30,82"},{"com":3,"dt_com":20240609190000,"enti_p":14,"enti_t":14,"perc":"26,55","vot_m":0,"vot_f":0,"vot_t":3244,"perc_r":"48,13"},{"com":4,"dt_com":20240609230000,"enti_p":14,"enti_t":14,"perc":"40,74","vot_m":2601,"vot_f":2377,"vot_t":4978,"perc_r":"48,13"}]},{"tipo":"COMUNE","desc":"LEPORANO","cod":100,"ele_m":3408,"ele_f":3416,"ele_t":6824,"una_lis":null,"tipo_tras":"SZ","com_vot":[{"com":1,"dt_com":20240608230000,"enti_p":6,"enti_t":6,"perc":"9,28","vot_m":0,"vot_f":0,"vot_t":633,"perc_r":"20,89"},{"com":2,"dt_com":20240609120000,"enti_p":6,"enti_t":6,"perc":"16,60","vot_m":0,"vot_f":0,"vot_t":1133,"perc_r":"58,17"},{"com":3,"dt_com":20240609190000,"enti_p":6,"enti_t":6,"perc":"25,34","vot_m":0,"vot_f":0,"vot_t":1729,"perc_r":"74,80"},{"com":4,"dt_com":20240609230000,"enti_p":6,"enti_t":6,"perc":"33,18","vot_m":1201,"vot_f":1063,"vot_t":2264,"perc_r":"74,80"}]},{"tipo":"COMUNE","desc":"LIZZANO","cod":110,"ele_m":3947,"ele_f":4212,"ele_t":8159,"una_lis":null,"tipo_tras":"SZ","com_vot":[{"com":1,"dt_com":20240608230000,"enti_p":9,"enti_t":9,"perc":"9,72","vot_m":0,"vot_f":0,"vot_t":793,"perc_r":"11,18"},{"com":2,"dt_com":20240609120000,"enti_p":9,"enti_t":9,"perc":"15,96","vot_m":0,"vot_f":0,"vot_t":1302,"perc_r":"33,96"},{"com":3,"dt_com":20240609190000,"enti_p":9,"enti_t":9,"perc":"25,15","vot_m":0,"vot_f":0,"vot_t":2052,"perc_r":"47,02"},{"com":4,"dt_com":20240609230000,"enti_p":9,"enti_t":9,"perc":"36,01","vot_m":1551,"vot_f":1387,"vot_t":2938,"perc_r":"47,02"}]},{"tipo":"COMUNE","desc":"MANDURIA","cod":120,"ele_m":12160,"ele_f":13126,"ele_t":25286,"una_lis":null,"tipo_tras":"SZ","com_vot":[{"com":1,"dt_com":20240608230000,"enti_p":30,"enti_t":30,"perc":"10,79","vot_m":0,"vot_f":0,"vot_t":2728,"perc_r":"11,71"},{"com":2,"dt_com":20240609120000,"enti_p":30,"enti_t":30,"perc":"17,96","vot_m":0,"vot_f":0,"vot_t":4541,"perc_r":"33,12"},{"com":3,"dt_com":20240609190000,"enti_p":30,"enti_t":30,"perc":"26,09","vot_m":0,"vot_f":0,"vot_t":6597,"perc_r":"44,13"},{"com":4,"dt_com":20240609230000,"enti_p":30,"enti_t":30,"perc":"36,17","vot_m":4694,"vot_f":4453,"vot_t":9147,"perc_r":"44,13"}]},{"tipo":"COMUNE","desc":"MARTINA FRANCA","cod":130,"ele_m":19460,"ele_f":20960,"ele_t":40420,"una_lis":null,"tipo_tras":"SZ","com_vot":[{"com":1,"dt_com":20240608230000,"enti_p":44,"enti_t":44,"perc":"11,34","vot_m":0,"vot_f":0,"vot_t":4585,"perc_r":"12,30"},{"com":2,"dt_com":20240609120000,"enti_p":44,"enti_t":44,"perc":"19,89","vot_m":0,"vot_f":0,"vot_t":8041,"perc_r":"32,96"},{"com":3,"dt_com":20240609190000,"enti_p":44,"enti_t":44,"perc":"31,12","vot_m":0,"vot_f":0,"vot_t":12577,"perc_r":"48,79"},{"com":4,"dt_com":20240609230000,"enti_p":44,"enti_t":44,"perc":"43,39","vot_m":8787,"vot_f":8752,"vot_t":17539,"perc_r":"48,79"}]},{"tipo":"COMUNE","desc":"MARUGGIO","cod":140,"ele_m":2217,"ele_f":2339,"ele_t":4556,"una_lis":null,"tipo_tras":"SZ","com_vot":[{"com":1,"dt_com":20240608230000,"enti_p":5,"enti_t":5,"perc":"25,15","vot_m":0,"vot_f":0,"vot_t":1146,"perc_r":"24,25"},{"com":2,"dt_com":20240609120000,"enti_p":5,"enti_t":5,"perc":"40,54","vot_m":0,"vot_f":0,"vot_t":1847,"perc_r":"59,42"},{"com":3,"dt_com":20240609190000,"enti_p":5,"enti_t":5,"perc":"57,75","vot_m":0,"vot_f":0,"vot_t":2631,"perc_r":"74,26"},{"com":4,"dt_com":20240609230000,"enti_p":5,"enti_t":5,"perc":"73,02","vot_m":1682,"vot_f":1645,"vot_t":3327,"perc_r":"74,26"}]},{"tipo":"COMUNE","desc":"MASSAFRA","cod":150,"ele_m":12480,"ele_f":13351,"ele_t":25831,"una_lis":null,"tipo_tras":"SZ","com_vot":[{"com":1,"dt_com":20240608230000,"enti_p":26,"enti_t":26,"perc":"10,00","vot_m":0,"vot_f":0,"vot_t":2583,"perc_r":"10,77"},{"com":2,"dt_com":20240609120000,"enti_p":26,"enti_t":26,"perc":"17,20","vot_m":0,"vot_f":0,"vot_t":4444,"perc_r":"29,52"},{"com":3,"dt_com":20240609190000,"enti_p":26,"enti_t":26,"perc":"25,59","vot_m":0,"vot_f":0,"vot_t":6609,"perc_r":"41,96"},{"com":4,"dt_com":20240609230000,"enti_p":26,"enti_t":26,"perc":"35,69","vot_m":4817,"vot_f":4402,"vot_t":9219,"perc_r":"41,96"}]},{"tipo":"COMUNE","desc":"MONTEIASI","cod":160,"ele_m":2196,"ele_f":2329,"ele_t":4525,"una_lis":null,"tipo_tras":"SZ","com_vot":[{"com":1,"dt_com":20240608230000,"enti_p":5,"enti_t":5,"perc":"9,79","vot_m":0,"vot_f":0,"vot_t":443,"perc_r":"11,92"},{"com":2,"dt_com":20240609120000,"enti_p":5,"enti_t":5,"perc":"17,06","vot_m":0,"vot_f":0,"vot_t":772,"perc_r":"29,88"},{"com":3,"dt_com":20240609190000,"enti_p":5,"enti_t":5,"perc":"26,76","vot_m":0,"vot_f":0,"vot_t":1211,"perc_r":"41,43"},{"com":4,"dt_com":20240609230000,"enti_p":5,"enti_t":5,"perc":"39,23","vot_m":958,"vot_f":817,"vot_t":1775,"perc_r":"41,43"}]},{"tipo":"COMUNE","desc":"MONTEMESOLA","cod":170,"ele_m":1468,"ele_f":1590,"ele_t":3058,"una_lis":null,"tipo_tras":"SZ","com_vot":[{"com":1,"dt_com":20240608230000,"enti_p":4,"enti_t":4,"perc":"9,32","vot_m":0,"vot_f":0,"vot_t":285,"perc_r":"9,34"},{"com":2,"dt_com":20240609120000,"enti_p":4,"enti_t":4,"perc":"15,99","vot_m":0,"vot_f":0,"vot_t":489,"perc_r":"29,03"},{"com":3,"dt_com":20240609190000,"enti_p":4,"enti_t":4,"perc":"24,17","vot_m":0,"vot_f":0,"vot_t":739,"perc_r":"40,49"},{"com":4,"dt_com":20240609230000,"enti_p":4,"enti_t":4,"perc":"34,01","vot_m":546,"vot_f":494,"vot_t":1040,"perc_r":"40,49"}]},{"tipo":"COMUNE","desc":"MONTEPARANO","cod":180,"ele_m":946,"ele_f":1007,"ele_t":1953,"una_lis":null,"tipo_tras":"SZ","com_vot":[{"com":1,"dt_com":20240608230000,"enti_p":2,"enti_t":2,"perc":"11,52","vot_m":0,"vot_f":0,"vot_t":225,"perc_r":"12,29"},{"com":2,"dt_com":20240609120000,"enti_p":2,"enti_t":2,"perc":"21,92","vot_m":0,"vot_f":0,"vot_t":428,"perc_r":"37,48"},{"com":3,"dt_com":20240609190000,"enti_p":2,"enti_t":2,"perc":"32,87","vot_m":0,"vot_f":0,"vot_t":642,"perc_r":"46,33"},{"com":4,"dt_com":20240609230000,"enti_p":2,"enti_t":2,"perc":"44,65","vot_m":436,"vot_f":436,"vot_t":872,"perc_r":"46,33"}]},{"tipo":"COMUNE","desc":"MOTTOLA","cod":190,"ele_m":6338,"ele_f":6812,"ele_t":13150,"una_lis":null,"tipo_tras":"SZ","com_vot":[{"com":1,"dt_com":20240608230000,"enti_p":18,"enti_t":18,"perc":"12,41","vot_m":0,"vot_f":0,"vot_t":1632,"perc_r":"10,09"},{"com":2,"dt_com":20240609120000,"enti_p":18,"enti_t":18,"perc":"21,70","vot_m":0,"vot_f":0,"vot_t":2853,"perc_r":"31,99"},{"com":3,"dt_com":20240609190000,"enti_p":18,"enti_t":18,"perc":"30,92","vot_m":0,"vot_f":0,"vot_t":4066,"perc_r":"49,36"},{"com":4,"dt_com":20240609230000,"enti_p":18,"enti_t":18,"perc":"44,56","vot_m":3028,"vot_f":2831,"vot_t":5859,"perc_r":"49,36"}]},{"tipo":"COMUNE","desc":"PALAGIANELLO","cod":200,"ele_m":3100,"ele_f":3289,"ele_t":6389,"una_lis":null,"tipo_tras":"SZ","com_vot":[{"com":1,"dt_com":20240608230000,"enti_p":6,"enti_t":6,"perc":"9,80","vot_m":0,"vot_f":0,"vot_t":626,"perc_r":"11,13"},{"com":2,"dt_com":20240609120000,"enti_p":6,"enti_t":6,"perc":"16,58","vot_m":0,"vot_f":0,"vot_t":1059,"perc_r":"29,72"},{"com":3,"dt_com":20240609190000,"enti_p":6,"enti_t":6,"perc":"24,03","vot_m":0,"vot_f":0,"vot_t":1535,"perc_r":"45,03"},{"com":4,"dt_com":20240609230000,"enti_p":6,"enti_t":6,"perc":"36,53","vot_m":1220,"vot_f":1114,"vot_t":2334,"perc_r":"45,03"}]},{"tipo":"COMUNE","desc":"PALAGIANO","cod":210,"ele_m":6120,"ele_f":6483,"ele_t":12603,"una_lis":null,"tipo_tras":"SZ","com_vot":[{"com":1,"dt_com":20240608230000,"enti_p":14,"enti_t":14,"perc":"10,57","vot_m":0,"vot_f":0,"vot_t":1332,"perc_r":"11,55"},{"com":2,"dt_com":20240609120000,"enti_p":14,"enti_t":14,"perc":"17,59","vot_m":0,"vot_f":0,"vot_t":2217,"perc_r":"31,47"},{"com":3,"dt_com":20240609190000,"enti_p":14,"enti_t":14,"perc":"24,85","vot_m":0,"vot_f":0,"vot_t":3132,"perc_r":"43,84"},{"com":4,"dt_com":20240609230000,"enti_p":14,"enti_t":14,"perc":"36,58","vot_m":2438,"vot_f":2172,"vot_t":4610,"perc_r":"43,84"}]},{"tipo":"COMUNE","desc":"PULSANO","cod":220,"ele_m":4666,"ele_f":4909,"ele_t":9575,"una_lis":null,"tipo_tras":"SZ","com_vot":[{"com":1,"dt_com":20240608230000,"enti_p":9,"enti_t":9,"perc":"8,46","vot_m":0,"vot_f":0,"vot_t":810,"perc_r":"12,04"},{"com":2,"dt_com":20240609120000,"enti_p":9,"enti_t":9,"perc":"15,97","vot_m":0,"vot_f":0,"vot_t":1529,"perc_r":"31,74"},{"com":3,"dt_com":20240609190000,"enti_p":9,"enti_t":9,"perc":"24,50","vot_m":0,"vot_f":0,"vot_t":2346,"perc_r":"42,00"},{"com":4,"dt_com":20240609230000,"enti_p":9,"enti_t":9,"perc":"33,49","vot_m":1709,"vot_f":1498,"vot_t":3207,"perc_r":"42,00"}]},{"tipo":"COMUNE","desc":"ROCCAFORZATA","cod":230,"ele_m":723,"ele_f":749,"ele_t":1472,"una_lis":null,"tipo_tras":"SZ","com_vot":[{"com":1,"dt_com":20240608230000,"enti_p":2,"enti_t":2,"perc":"9,85","vot_m":0,"vot_f":0,"vot_t":145,"perc_r":"27,51"},{"com":2,"dt_com":20240609120000,"enti_p":2,"enti_t":2,"perc":"17,46","vot_m":0,"vot_f":0,"vot_t":257,"perc_r":"64,78"},{"com":3,"dt_com":20240609190000,"enti_p":2,"enti_t":2,"perc":"27,11","vot_m":0,"vot_f":0,"vot_t":399,"perc_r":"82,12"},{"com":4,"dt_com":20240609230000,"enti_p":2,"enti_t":2,"perc":"38,93","vot_m":298,"vot_f":275,"vot_t":573,"perc_r":"82,12"}]},{"tipo":"COMUNE","desc":"SAN GIORGIO IONICO","cod":240,"ele_m":5652,"ele_f":6231,"ele_t":11883,"una_lis":null,"tipo_tras":"SZ","com_vot":[{"com":1,"dt_com":20240608230000,"enti_p":13,"enti_t":13,"perc":"10,85","vot_m":0,"vot_f":0,"vot_t":1289,"perc_r":"11,57"},{"com":2,"dt_com":20240609120000,"enti_p":13,"enti_t":13,"perc":"17,75","vot_m":0,"vot_f":0,"vot_t":2109,"perc_r":"29,03"},{"com":3,"dt_com":20240609190000,"enti_p":13,"enti_t":13,"perc":"26,44","vot_m":0,"vot_f":0,"vot_t":3142,"perc_r":"42,76"},{"com":4,"dt_com":20240609230000,"enti_p":13,"enti_t":13,"perc":"36,18","vot_m":2176,"vot_f":2123,"vot_t":4299,"perc_r":"42,76"}]},{"tipo":"COMUNE","desc":"SAN MARZANO DI SAN GIUSEPPE","cod":250,"ele_m":3640,"ele_f":3751,"ele_t":7391,"una_lis":null,"tipo_tras":"SZ","com_vot":[{"com":1,"dt_com":20240608230000,"enti_p":8,"enti_t":8,"perc":"8,85","vot_m":0,"vot_f":0,"vot_t":654,"perc_r":"9,08"},{"com":2,"dt_com":20240609120000,"enti_p":8,"enti_t":8,"perc":"15,48","vot_m":0,"vot_f":0,"vot_t":1144,"perc_r":"30,89"},{"com":3,"dt_com":20240609190000,"enti_p":8,"enti_t":8,"perc":"23,92","vot_m":0,"vot_f":0,"vot_t":1768,"perc_r":"44,69"},{"com":4,"dt_com":20240609230000,"enti_p":8,"enti_t":8,"perc":"35,80","vot_m":1420,"vot_f":1226,"vot_t":2646,"perc_r":"44,69"}]},{"tipo":"COMUNE","desc":"SAVA","cod":260,"ele_m":6407,"ele_f":6966,"ele_t":13373,"una_lis":null,"tipo_tras":"SZ","com_vot":[{"com":1,"dt_com":20240608230000,"enti_p":15,"enti_t":15,"perc":"12,14","vot_m":0,"vot_f":0,"vot_t":1623,"perc_r":"9,60"},{"com":2,"dt_com":20240609120000,"enti_p":15,"enti_t":15,"perc":"19,84","vot_m":0,"vot_f":0,"vot_t":2653,"perc_r":"28,11"},{"com":3,"dt_com":20240609190000,"enti_p":15,"enti_t":15,"perc":"28,06","vot_m":0,"vot_f":0,"vot_t":3753,"perc_r":"40,99"},{"com":4,"dt_com":20240609230000,"enti_p":15,"enti_t":15,"perc":"39,33","vot_m":2676,"vot_f":2584,"vot_t":5260,"perc_r":"40,99"}]},{"tipo":"COMUNE","desc":"STATTE","cod":261,"ele_m":5088,"ele_f":5586,"ele_t":10674,"una_lis":null,"tipo_tras":"SZ","com_vot":[{"com":1,"dt_com":20240608230000,"enti_p":13,"enti_t":13,"perc":"18,47","vot_m":0,"vot_f":0,"vot_t":1972,"perc_r":"10,52"},{"com":2,"dt_com":20240609120000,"enti_p":13,"enti_t":13,"perc":"29,83","vot_m":0,"vot_f":0,"vot_t":3184,"perc_r":"29,84"},{"com":3,"dt_com":20240609190000,"enti_p":13,"enti_t":13,"perc":"41,30","vot_m":0,"vot_f":0,"vot_t":4408,"perc_r":"42,77"},{"com":4,"dt_com":20240609230000,"enti_p":13,"enti_t":13,"perc":"56,32","vot_m":2990,"vot_f":3022,"vot_t":6012,"perc_r":"42,77"}]},{"tipo":"COMUNE","desc":"TARANTO","cod":270,"ele_m":74128,"ele_f":83367,"ele_t":157495,"una_lis":null,"tipo_tras":"SZ","com_vot":[{"com":1,"dt_com":20240608230000,"enti_p":191,"enti_t":191,"perc":"10,12","vot_m":0,"vot_f":0,"vot_t":15931,"perc_r":"11,15"},{"com":2,"dt_com":20240609120000,"enti_p":191,"enti_t":191,"perc":"17,74","vot_m":0,"vot_f":0,"vot_t":27947,"perc_r":"28,73"},{"com":3,"dt_com":20240609190000,"enti_p":191,"enti_t":191,"perc":"26,24","vot_m":0,"vot_f":0,"vot_t":41330,"perc_r":"39,87"},{"com":4,"dt_com":20240609230000,"enti_p":191,"enti_t":191,"perc":"35,19","vot_m":28043,"vot_f":27375,"vot_t":55418,"perc_r":"39,87"}]},{"tipo":"COMUNE","desc":"TORRICELLA","cod":280,"ele_m":1733,"ele_f":1768,"ele_t":3501,"una_lis":null,"tipo_tras":"SZ","com_vot":[{"com":1,"dt_com":20240608230000,"enti_p":5,"enti_t":5,"perc":"8,57","vot_m":0,"vot_f":0,"vot_t":300,"perc_r":"11,58"},{"com":2,"dt_com":20240609120000,"enti_p":5,"enti_t":5,"perc":"15,97","vot_m":0,"vot_f":0,"vot_t":559,"perc_r":"33,22"},{"com":3,"dt_com":20240609190000,"enti_p":5,"enti_t":5,"perc":"26,36","vot_m":0,"vot_f":0,"vot_t":923,"perc_r":"47,75"},{"com":4,"dt_com":20240609230000,"enti_p":5,"enti_t":5,"perc":"37,08","vot_m":705,"vot_f":593,"vot_t":1298,"perc_r":"47,75"}]}]}}
